django_directory_cms/__init__.py
django_directory_cms/admin.py
django_directory_cms/apps.py
django_directory_cms/context_processors.py
django_directory_cms/models.py
django_directory_cms/urls.py
django_directory_cms/views.py
django_directory_cms/migrations/0001_initial.py
django_directory_cms/migrations/__init__.py
django_directory_cms/templates/django_directory_cms/pages/page_detail.html
django_directory_cms/templates/django_directory_cms/pages/page_list.html
django_directory_cms-0.2.0.dist-info/METADATA
django_directory_cms-0.2.0.dist-info/WHEEL
django_directory_cms-0.2.0.dist-info/licenses/LICENSE
django_directory_cms-0.2.0.dist-info/RECORD
