Metadata-Version: 2.4
Name: django-directory-cms
Version: 0.2.0
Summary: Reusable Django CMS package with SEO-optimized pages and hierarchical menus
Project-URL: Homepage, https://github.com/directory-platform/django-directory-cms
Project-URL: Repository, https://github.com/directory-platform/django-directory-cms
Project-URL: Issues, https://github.com/directory-platform/django-directory-cms/issues
Author: Directory Platform Team
License: MIT
License-File: LICENSE
Keywords: cms,content-management,django,menus,pages,seo
Classifier: Development Status :: 4 - Beta
Classifier: Environment :: Web Environment
Classifier: Framework :: Django
Classifier: Framework :: Django :: 4.2
Classifier: Framework :: Django :: 5.0
Classifier: Framework :: Django :: 5.1
Classifier: Intended Audience :: Developers
Classifier: License :: OSI Approved :: MIT License
Classifier: Operating System :: OS Independent
Classifier: Programming Language :: Python
Classifier: Programming Language :: Python :: 3
Classifier: Programming Language :: Python :: 3.12
Classifier: Topic :: Internet :: WWW/HTTP
Classifier: Topic :: Internet :: WWW/HTTP :: Dynamic Content
Classifier: Topic :: Internet :: WWW/HTTP :: Site Management
Classifier: Typing :: Typed
Requires-Python: >=3.12
Requires-Dist: django-seo-audit>=0.2.0
Requires-Dist: django>=4.2
Requires-Dist: pillow>=10.0.0
Provides-Extra: dev
Requires-Dist: django-stubs>=4.2.0; extra == 'dev'
Requires-Dist: mypy>=1.7.0; extra == 'dev'
Requires-Dist: ruff>=0.1.0; extra == 'dev'
